blender_connect_mcp-1.2.5.dist-info/licenses/LICENSE
blender_mcp/__init__.py
blender_mcp/config.py
blender_mcp/connection.py
blender_mcp/exceptions.py
blender_mcp/models.py
blender_mcp/server.py
blender_mcp/tools/__init__.py
blender_mcp/tools/base.py
blender_mcp/tools/hyper3d_tools.py
blender_mcp/tools/polyhaven_tools.py
blender_mcp/tools/scene_tools.py
blender_mcp/tools/sketchfab_tools.py
blender_mcp/utils/__init__.py
blender_mcp/utils/logging.py
blender_mcp/utils/validation.py
blender_connect_mcp-1.2.5.dist-info/METADATA
blender_connect_mcp-1.2.5.dist-info/WHEEL
blender_connect_mcp-1.2.5.dist-info/entry_points.txt
blender_connect_mcp-1.2.5.dist-info/top_level.txt
blender_connect_mcp-1.2.5.dist-info/RECORD
